py_subwasm_bindings-0.0.3.dist-info/METADATA
py_subwasm_bindings-0.0.3.dist-info/WHEEL
subwasm/__init__.py
subwasm/subwasm.cpython-36m-aarch64-linux-gnu.so
py_subwasm_bindings-0.0.3.dist-info/RECORD
