Metadata-Version: 2.1
Name: py-subwasm-bindings
Version: 0.0.3
Classifier: License :: OSI Approved :: Apache Software License
Classifier: Intended Audience :: Developers
Classifier: Programming Language :: Python :: 3
Classifier: Programming Language :: Python :: 3.6
Classifier: Programming Language :: Python :: 3.7
Classifier: Programming Language :: Python :: 3.8
Classifier: Programming Language :: Python :: 3.9
Summary: Python bindings for subwasm library
Home-Page: https://github.com/polkascan/py-subwasm-bindings
Author: Polkascan Foundation
Maintainer: Stichting Polkascan (Polkascan Foundation)
Maintainer-email: legal@polkascan.org
License: Apache-2.0
Project-URL: Source Code, https://github.com/polkascan/py-subwasm-bindings
